LICENSE
MANIFEST.in
README.rst
doc-requirements.txt
requirements.txt
setup.cfg
setup.py
test-requirements.txt
versioneer.py
sphinxtesters/__init__.py
sphinxtesters/_version.py
sphinxtesters/sphinxutils.py
sphinxtesters/tmpdirs.py
sphinxtesters.egg-info/PKG-INFO
sphinxtesters.egg-info/SOURCES.txt
sphinxtesters.egg-info/dependency_links.txt
sphinxtesters.egg-info/requires.txt
sphinxtesters.egg-info/top_level.txt
sphinxtesters/tests/__init__.py
sphinxtesters/tests/test_modified_pagebuilder.py
sphinxtesters/tests/test_pagebuilder.py
sphinxtesters/tests/test_proj1.py
sphinxtesters/tests/test_sources_builder.py
sphinxtesters/tests/test_testapp.py
sphinxtesters/tests/test_tmpdirs.py
sphinxtesters/tests/proj1/.gitignore
sphinxtesters/tests/proj1/README.md
sphinxtesters/tests/proj1/a_page.rst
sphinxtesters/tests/proj1/conf.py
sphinxtesters/tests/proj1/index.rst
sphinxtesters/tests/proj1/_static/.gitignore
sphinxtesters/tests/proj1/_static/README.txt