Metadata-Version: 2.1
Name: sphinxtesters
Version: 0.2.3
Summary: Utilities for testing Sphinx extensions
Home-page: http://github.com/matthew-brett/sphinxtesters
Author: Matthew Brett
Author-email: matthew.brett@gmail.com
Maintainer: Matthew Brett
Maintainer-email: matthew.brett@gmail.com
License: BSD license
Platform: UNKNOWN
Classifier: Development Status :: 2 - Pre-Alpha
Classifier: Environment :: Console
Classifier: Intended Audience :: Developers
Classifier: Intended Audience :: Science/Research
Classifier: License :: OSI Approved :: BSD License
Classifier: Programming Language :: Python
Classifier: Programming Language :: Python :: 3
Classifier: Topic :: Scientific/Engineering
Classifier: Operating System :: Microsoft :: Windows
Classifier: Operating System :: POSIX
Classifier: Operating System :: Unix
Classifier: Operating System :: MacOS
Provides-Extra: test
